opscidia_elasticsearch/__init__.py
opscidia_elasticsearch/manager.py
opscidia_elasticsearch/features/__init__.py
opscidia_elasticsearch/features/app_features.py
opscidia_elasticsearch/settings/settings v1.json
opscidia_elasticsearch-1.0.3.dist-info/LICENSE
opscidia_elasticsearch-1.0.3.dist-info/METADATA
opscidia_elasticsearch-1.0.3.dist-info/WHEEL
opscidia_elasticsearch-1.0.3.dist-info/top_level.txt
opscidia_elasticsearch-1.0.3.dist-info/RECORD
