Metadata-Version: 2.1
Name: opscidia-elasticsearch
Version: 1.0.3
Summary: Tools to manage elasticsearch indexes
Author: Opscidia (Tech)
Author-email: tech@opscidia.com
Maintainer: Fréjus Laleye
Maintainer-email: frejus.Laleye@opscidia.com
License: UNKNOWN
Keywords: elasticsearch,ospcidia,index,create
Platform: UNKNOWN
Classifier: Development Status :: 3 - Alpha
Classifier: Intended Audience :: Developers
Classifier: Programming Language :: Python :: 3
Classifier: Operating System :: OS Independent
Requires-Python: >=3.7
License-File: LICENSE
Requires-Dist: beautifulsoup4
Requires-Dist: boto3
Requires-Dist: elasticsearch (==7.12.0)
Requires-Dist: elasticsearch-dsl (==7.3.0)
Requires-Dist: requests-aws4auth
Requires-Dist: tqdm
